tree_sitter_gh_actions_expressions/__init__.py
tree_sitter_gh_actions_expressions/__init__.pyi
tree_sitter_gh_actions_expressions/_binding.abi3.so
tree_sitter_gh_actions_expressions/binding.c
tree_sitter_gh_actions_expressions/py.typed
tree_sitter_gh_actions_expressions/queries/highlights.scm
tree_sitter_gh_actions_expressions/queries/injections.scm
tree_sitter_gh_actions_expressions-0.5.1.dist-info/METADATA
tree_sitter_gh_actions_expressions-0.5.1.dist-info/WHEEL
tree_sitter_gh_actions_expressions-0.5.1.dist-info/top_level.txt
tree_sitter_gh_actions_expressions-0.5.1.dist-info/RECORD
tree_sitter_gh_actions_expressions-0.5.1.dist-info/licenses/LICENSE
