Metadata-Version: 2.4
Name: tree-sitter-gh-actions-expressions
Version: 0.5.1
Summary: Github Actions expressions grammar for tree-sitter
Author-email: Héctor Ochoa <hector.ochoa.dev@gmail.com>
License: MIT
Project-URL: Homepage, https://github.com/hdoc1509/tree-sitter-gh-actions-expressions
Keywords: incremental,parsing,tree-sitter,gh-actions-expressions
Classifier: Intended Audience :: Developers
Classifier: Topic :: Software Development :: Compilers
Classifier: Topic :: Text Processing :: Linguistic
Classifier: Typing :: Typed
Requires-Python: >=3.10
License-File: LICENSE
Provides-Extra: core
Requires-Dist: tree-sitter~=0.24; extra == "core"
Dynamic: license-file
